testgithook
